themis.finals.checker.app-1.5.0-py3.5-nspkg.pth
themis/finals/checker/app/__about__.py
themis/finals/checker/app/__init__.py
themis/finals/checker/app/loader.py
themis/finals/checker/app/server.py
themis/finals/checker/app/worker.py
themis.finals.checker.app-1.5.0.dist-info/METADATA
themis.finals.checker.app-1.5.0.dist-info/RECORD
themis.finals.checker.app-1.5.0.dist-info/WHEEL
themis.finals.checker.app-1.5.0.dist-info/entry_points.txt
themis.finals.checker.app-1.5.0.dist-info/namespace_packages.txt
themis.finals.checker.app-1.5.0.dist-info/top_level.txt
