Metadata-Version: 2.1
Name: themis.finals.checker.app
Version: 1.5.0
Summary: Themis Finals checker application
Home-page: https://github.com/themis-project/themis-finals-checker-app-py
Author: Alexander Pyatkin
Author-email: aspyatkin@gmail.com
License: MIT
Platform: UNKNOWN
Requires-Dist: setuptools (>=0.8)
Requires-Dist: Flask (<0.12,>=0.11.1)
Requires-Dist: redis (<2.11,>=2.10.5)
Requires-Dist: hiredis (<0.3,>=0.2.0)
Requires-Dist: rq (<0.8.0,>=0.7.1)
Requires-Dist: requests (>=2.11.0)
Requires-Dist: python-dateutil (<2.6,>=2.5.3)
Requires-Dist: themis.finals.checker.result (==1.1.0)
Requires-Dist: raven (<5.27.0,>=5.26.0)
Requires-Dist: PyJWT (<1.6.0,>=1.5.0)
Requires-Dist: cryptography (<1.9.0,>=1.8.1)
Requires-Dist: PyYAML (>=3.11)
